Workbook

Sheet Начать здесь
A1: STIMUL FOOD — финансовая модель
A2: 36 месяцев + первые 13 недель. Все прогнозы являются расчётной моделью и заменяются фактическими данными по мере запуска.
A5: Что менять | B5: Только синие ячейки на листе «Исходные данные». Формулы не перезаписывать.
A6: Основной вывод | B6: При цене и целевых закупочных условиях проект выходит на операционную безубыточность примерно при 45–50 рационах в рабочий день.
A7: Потребность в финансировании | B7: 68,000 бел. руб. — расчётный бюджет запуска, производства, продвижения и оборотного капитала.
A8: Приоритет | B8: Сначала подтвердить кухню, выходы и фактическую себестоимость; затем увеличивать рекламный бюджет.

Sheet Исходные данные
A1: Исходные данные
A2: Синие значения можно менять. Жёлтая заливка означает: требуется подтвердить договором, коммерческим предложением или пилотом.
A4: Код | B4: Показатель | C4: Осторожный | D4: Основной | E4: Успешный | F4: Единица | G4: Источник/логика | H4: Комментарий | J4: Выбранный сценарий
A5: A01 | B5: Средняя цена дня | C5: 43.5 | D5: 44.35 | E5: 45.2 | F5: бел. руб. | G5: Цены пакетов | J5: Основной
A6: A02 | B6: Сырьё при малом объёме | C6: 16.5 | D6: 15.45 | E6: 14.5 | F6: бел. руб./день | G6: Меню и открытые цены
B7: Сырьё при устойчивом объёме | C7: 14.2 | D7: 13.35 | E7: 12.7 | F7: бел. руб./день | G7: Оптовый расчёт | H7: Требуется КП | J7: Код | K7: Выбранное значение
A8: A04 | B8: Кухня при малом объёме | C8: 8 | D8: 6.5 | E8: 6 | F8: бел. руб./день | G8: Диапазон переговоров | H8: Требуется КП | J8: A01 | K8: =IF($J$5="Осторожный",C5,IF($J$5="Успешный",E5,D5)) -> 44.35
A9: A05 | B9: Кухня при устойчивом объёме | C9: 6.5 | D9: 5.5 | E9: 4.8 | F9: бел. руб./день | G9: Диапазон переговоров | H9: Требуется КП | J9: A02 | K9: =IF($J$5="Осторожный",C6,IF($J$5="Успешный",E6,D6)) -> 15.45
A10: A06 | B10: Упаковка при малом объёме | C10: 4.2 | D10: 3.65 | E10: 3.4 | F10: бел. руб./день | G10: 5 контейнеров + этикетки + общий пакет | H10: Требуется КП | J10: A03 | K10: =IF($J$5="Осторожный",C7,IF($J$5="Успешный",E7,D7)) -> 13.35
A11: A07 | B11: Упаковка при устойчивом объёме | C11: 3.7 | D11: 3.2 | E11: 2.9 | F11: бел. руб./день | G11: Оптовый расчёт | H11: Требуется КП | J11: A04 | K11: =IF($J$5="Осторожный",C8,IF($J$5="Успешный",E8,D8)) -> 6.5
A12: A08 | B12: Доставка при малом объёме | C12: 4.5 | D12: 3.4 | E12: 3 | F12: бел. руб./день | G12: Маршрутный расчёт | H12: Требуется тест | J12: A05 | K12: =IF($J$5="Осторожный",C9,IF($J$5="Успешный",E9,D9)) -> 5.5
A13: A09 | B13: Доставка при устойчивом объёме | C13: 3.5 | D13: 2.8 | E13: 2.4 | F13: бел. руб./день | G13: Плотность маршрута | H13: Требуется тест | J13: A06 | K13: =IF($J$5="Осторожный",C10,IF($J$5="Успешный",E10,D10)) -> 3.65
A14: A10 | B14: Прочие переменные расходы | C14: 1.8 | D14: 1.5 | E14: 1.3 | F14: бел. руб./день | G14: Расходники и поддержка | J14: A07 | K14: =IF($J$5="Осторожный",C11,IF($J$5="Успешный",E11,D11)) -> 3.2
A15: A11 | B15: Списания и отклонения | C15: 0.05 | D15: 0.03 | E15: 0.02 | F15: % сырья | G15: Целевой уровень | J15: A08 | K15: =IF($J$5="Осторожный",C12,IF($J$5="Успешный",E12,D12)) -> 3.4
A16: A12 | B16: Комиссия оплаты | C16: 0.022 | D16: 0.018 | E16: 0.015 | F16: % выручки | G16: Платёжный провайдер | J16: A09 | K16: =IF($J$5="Осторожный",C13,IF($J$5="Успешный",E13,D13)) -> 2.8
A17: A13 | B17: Налоговый сценарий | C17: 0.08 | D17: 0.06 | E17: 0.04 | F17: % выручки | G17: Зависит от формы бизнеса | H17: Проверить с бухгалтером | J17: A10 | K17: =IF($J$5="Осторожный",C14,IF($J$5="Успешный",E14,D14)) -> 1.5
A18: A14 | B18: Стоимость заявки | C18: 7 | D18: 5.5 | E18: 4.5 | F18: бел. руб./заявка | G18: Рекламный тест | J18: A11 | K18: =IF($J$5="Осторожный",C15,IF($J$5="Успешный",E15,D15)) -> 0.03
A19: A15 | B19: Заявка → первый заказ | C19: 0.16 | D19: 0.22 | E19: 0.28 | F19: % | G19: Рекламный тест | J19: A12 | K19: =IF($J$5="Осторожный",C16,IF($J$5="Успешный",E16,D16)) -> 0.018
A20: A16 | B20: Повтор в следующем месяце | C20: 0.28 | D20: 0.4 | E20: 0.52 | F20: % | G20: Пилот | J20: A13 | K20: =IF($J$5="Осторожный",C17,IF($J$5="Успешный",E17,D17)) -> 0.06
A21: A17 | B21: Повтор во втором месяце | C21: 0.15 | D21: 0.25 | E21: 0.35 | F21: % | G21: Пилот | J21: A14 | K21: =IF($J$5="Осторожный",C18,IF($J$5="Успешный",E18,D18)) -> 5.5
A22: A18 | B22: Долгий повтор | C22: 0.08 | D22: 0.15 | E22: 0.22 | F22: % | G22: Пилот | J22: A15 | K22: =IF($J$5="Осторожный",C19,IF($J$5="Успешный",E19,D19)) -> 0.22
A23: A19 | B23: Рацион-дней на активного клиента | C23: 4 | D23: 5 | E23: 6 | F23: дней/мес | G23: Пилот | J23: A16 | K23: =IF($J$5="Осторожный",C20,IF($J$5="Успешный",E20,D20)) -> 0.4
A24: A20 | B24: Рабочих дней | C24: 24 | D24: 26 | E24: 27 | F24: дней/мес | G24: Календарь | J24: A17 | K24: =IF($J$5="Осторожный",C21,IF($J$5="Успешный",E21,D21)) -> 0.25
A25: A21 | B25: Постоянные расходы на зрелом этапе | C25: 14000 | D25: 12000 | E25: 11500 | F25: бел. руб./мес | G25: Штат, программы, управление | J25: A18 | K25: =IF($J$5="Осторожный",C22,IF($J$5="Успешный",E22,D22)) -> 0.15
A26: A22 | B26: Целевой денежный резерв | C26: 12000 | D26: 10000 | E26: 9000 | F26: бел. руб. | G26: Управленческий резерв | J26: A19 | K26: =IF($J$5="Осторожный",C23,IF($J$5="Успешный",E23,D23)) -> 5
J27: A20 | K27: =IF($J$5="Осторожный",C24,IF($J$5="Успешный",E24,D24)) -> 26
J28: A21 | K28: =IF($J$5="Осторожный",C25,IF($J$5="Успешный",E25,D25)) -> 12000
J29: A22 | K29: =IF($J$5="Осторожный",C26,IF($J$5="Успешный",E26,D26)) -> 10000

Sheet Экономика дня
A1: Экономика одного рациона
A2: Сравнение пилотного и устойчивого объёма. Показатели автоматически берутся из выбранного сценария.
A4: Показатель | B4: Пилот: малый объём | C4: Устойчивый объём | D4: Единица | E4: Доля в цене | F4: Комментарий | G4: Контроль
A5: Средняя цена | B5: =INDEX('Исходные данные'!$K$8:$K$29,MATCH("A01",'Исходные данные'!$J$8:$J$29,0)) -> 44.35 | C5: =INDEX('Исходные данные'!$K$8:$K$29,MATCH("A01",'Исходные данные'!$J$8:$J$29,0)) -> 44.35 | D5: бел. руб. | E5: =B5/B$5 -> 1 | G5: =IF(OR(B5<0,C5<0),"ПРОВЕРИТЬ","ПРОЙДЕНО") -> ПРОЙДЕНО
A6: Сырьё | B6: =INDEX('Исходные данные'!$K$8:$K$29,MATCH("A02",'Исходные данные'!$J$8:$J$29,0)) -> 15.45 | C6: =INDEX('Исходные данные'!$K$8:$K$29,MATCH("A03",'Исходные данные'!$J$8:$J$29,0)) -> 13.35 | D6: бел. руб. | E6: =B6/B$5 -> 0.34836528 | G6: =IF(OR(B6<0,C6<0),"ПРОВЕРИТЬ","ПРОЙДЕНО") -> ПРОЙДЕНО
A7: Работа кухни | B7: =INDEX('Исходные данные'!$K$8:$K$29,MATCH("A04",'Исходные данные'!$J$8:$J$29,0)) -> 6.5 | C7: =INDEX('Исходные данные'!$K$8:$K$29,MATCH("A05",'Исходные данные'!$J$8:$J$29,0)) -> 5.5 | D7: бел. руб. | E7: =B7/B$5 -> 0.14656144 | G7: =IF(OR(B7<0,C7<0),"ПРОВЕРИТЬ","ПРОЙДЕНО") -> ПРОЙДЕНО
A8: Упаковка | B8: =INDEX('Исходные данные'!$K$8:$K$29,MATCH("A06",'Исходные данные'!$J$8:$J$29,0)) -> 3.65 | C8: =INDEX('Исходные данные'!$K$8:$K$29,MATCH("A07",'Исходные данные'!$J$8:$J$29,0)) -> 3.2 | D8: бел. руб. | E8: =B8/B$5 -> 0.082299887 | G8: =IF(OR(B8<0,C8<0),"ПРОВЕРИТЬ","ПРОЙДЕНО") -> ПРОЙДЕНО
A9: Доставка | B9: =INDEX('Исходные данные'!$K$8:$K$29,MATCH("A08",'Исходные данные'!$J$8:$J$29,0)) -> 3.4 | C9: =INDEX('Исходные данные'!$K$8:$K$29,MATCH("A09",'Исходные данные'!$J$8:$J$29,0)) -> 2.8 | D9: бел. руб. | E9: =B9/B$5 -> 0.076662909 | G9: =IF(OR(B9<0,C9<0),"ПРОВЕРИТЬ","ПРОЙДЕНО") -> ПРОЙДЕНО
A10: Прочие переменные | B10: =INDEX('Исходные данные'!$K$8:$K$29,MATCH("A10",'Исходные данные'!$J$8:$J$29,0)) -> 1.5 | C10: =INDEX('Исходные данные'!$K$8:$K$29,MATCH("A10",'Исходные данные'!$J$8:$J$29,0)) -> 1.5 | D10: бел. руб. | E10: =B10/B$5 -> 0.033821871 | G10: =IF(OR(B10<0,C10<0),"ПРОВЕРИТЬ","ПРОЙДЕНО") -> ПРОЙДЕНО
A11: Списания | B11: =B6*INDEX('Исходные данные'!$K$8:$K$29,MATCH("A11",'Исходные данные'!$J$8:$J$29,0)) -> 0.4635 | C11: =C6*INDEX('Исходные данные'!$K$8:$K$29,MATCH("A11",'Исходные данные'!$J$8:$J$29,0)) -> 0.4005 | D11: бел. руб. | E11: =B11/B$5 -> 0.010450958 | G11: =IF(OR(B11<0,C11<0),"ПРОВЕРИТЬ","ПРОЙДЕНО") -> ПРОЙДЕНО
A12: Комиссия оплаты | B12: =B5*INDEX('Исходные данные'!$K$8:$K$29,MATCH("A12",'Исходные данные'!$J$8:$J$29,0)) -> 0.7983 | C12: =C5*INDEX('Исходные данные'!$K$8:$K$29,MATCH("A12",'Исходные данные'!$J$8:$J$29,0)) -> 0.7983 | D12: бел. руб. | E12: =B12/B$5 -> 0.018 | G12: =IF(OR(B12<0,C12<0),"ПРОВЕРИТЬ","ПРОЙДЕНО") -> ПРОЙДЕНО
A13: Налоговый сценарий | B13: =B5*INDEX('Исходные данные'!$K$8:$K$29,MATCH("A13",'Исходные данные'!$J$8:$J$29,0)) -> 2.661 | C13: =C5*INDEX('Исходные данные'!$K$8:$K$29,MATCH("A13",'Исходные данные'!$J$8:$J$29,0)) -> 2.661 | D13: бел. руб. | E13: =B13/B$5 -> 0.06 | G13: =IF(OR(B13<0,C13<0),"ПРОВЕРИТЬ","ПРОЙДЕНО") -> ПРОЙДЕНО
A14: Переменные расходы | B14: =SUM(B6:B13) -> 34.4228 | C14: =SUM(C6:C13) -> 30.2098 | D14: бел. руб. | E14: =B14/B$5 -> 0.77616234 | G14: =IF(OR(B14<0,C14<0),"ПРОВЕРИТЬ","ПРОЙДЕНО") -> ПРОЙДЕНО
A15: Вклад на покрытие | B15: =B5-B14 -> 9.9272 | C15: =C5-C14 -> 14.1402 | D15: бел. руб. | E15: =B15/B$5 -> 0.22383766 | G15: =IF(OR(B15<0,C15<0),"ПРОВЕРИТЬ","ПРОЙДЕНО") -> ПРОЙДЕНО
A16: Маржа вклада | B16: =B15/B5 -> 0.22383766 | C16: =C15/C5 -> 0.31883202 | D16: % | E16: =B16/B$5 -> 0.0050470723 | F16: Цель устойчивого объёма: не ниже 25% | G16: =IF(OR(B16<0,C16<0),"ПРОВЕРИТЬ","ПРОЙДЕНО") -> ПРОЙДЕНО
A17: Точка безубыточности в месяц | B17: =ROUNDUP(INDEX('Исходные данные'!$K$8:$K$29,MATCH("A21",'Исходные данные'!$J$8:$J$29,0))/B15,0) -> 1209 | C17: =ROUNDUP(INDEX('Исходные данные'!$K$8:$K$29,MATCH("A21",'Исходные данные'!$J$8:$J$29,0))/C15,0) -> 849 | D17: рацион-дней | E17: =B17/B$5 -> 27.260428 | G17: =IF(OR(B17<0,C17<0),"ПРОВЕРИТЬ","ПРОЙДЕНО") -> ПРОЙДЕНО
A18: Точка безубыточности в день | B18: =B17/INDEX('Исходные данные'!$K$8:$K$29,MATCH("A20",'Исходные данные'!$J$8:$J$29,0)) -> 46.5 | C18: =C17/INDEX('Исходные данные'!$K$8:$K$29,MATCH("A20",'Исходные данные'!$J$8:$J$29,0)) -> 32.653846 | D18: рационов/день | E18: =B18/B$5 -> 1.048478 | G18: =IF(OR(B18<0,C18<0),"ПРОВЕРИТЬ","ПРОЙДЕНО") -> ПРОЙДЕНО

Sheet Меню и себестоимость
A1: STIMUL FOOD — меню и себестоимость 70 блюд
A2: Связующий лист: названия, пищевые показатели и стоимость полностью совпадают с основным меню и сайтами.
A4: Код | B4: День | C4: Приём | D4: Название | E4: Ккал | F4: Белки | G4: Жиры | H4: Углеводы | I4: Розница | J4: Малый объём | K4: Опт | L4: Статус
A5: SF-D01-M01 | B5: 1 | C5: Завтрак | D5: Овсяная каша с ягодами | E5: 335 | F5: 12 | G5: 11.3 | H5: 48.6 | I5: 1.82 | J5: 1.61 | K5: 1.39 | L5: Расчёт
A6: SF-D01-M02 | B6: 1 | C6: Второй завтрак | D6: Творожный крем с яблоком | E6: 219 | F6: 20.5 | G6: 6.4 | H6: 22.6 | I6: 1.81 | J6: 1.6 | K6: 1.38 | L6: Расчёт
A7: SF-D01-M03 | B7: 1 | C7: Обед | D7: Индейка, гречка и овощи | E7: 472 | F7: 46.4 | G7: 10.8 | H7: 51.6 | I7: 5.14 | J7: 4.52 | K7: 3.91 | L7: Расчёт
A8: SF-D01-M04 | B8: 1 | C8: Полдник | D8: Салат с зеленью | E8: 179 | F8: 9.9 | G8: 12.5 | H8: 8.5 | I8: 2.6 | J8: 2.29 | K8: 1.98 | L8: Расчёт
A9: SF-D01-M05 | B9: 1 | C9: Ужин | D9: Рыба с картофелем | E9: 377 | F9: 35.3 | G9: 7.5 | H9: 43 | I9: 5.33 | J9: 4.69 | K9: 4.05 | L9: Расчёт
A10: SF-D02-M01 | B10: 2 | C10: Завтрак | D10: Сырники и йогурт | E10: 352 | F10: 31.6 | G10: 14 | H10: 26.1 | I10: 2.52 | J10: 2.22 | K10: 1.92 | L10: Расчёт
A11: SF-D02-M02 | B11: 2 | C11: Второй завтрак | D11: Груша и ореховый крем | E11: 224 | F11: 15.1 | G11: 8.9 | H11: 24.4 | I11: 1.76 | J11: 1.55 | K11: 1.34 | L11: Расчёт
A12: SF-D02-M03 | B12: 2 | C12: Обед | D12: Курица с булгуром | E12: 473 | F12: 44.7 | G12: 11.4 | H12: 49.6 | I12: 4.22 | J12: 3.71 | K12: 3.21 | L12: Расчёт
A13: SF-D02-M04 | B13: 2 | C13: Полдник | D13: Овощные палочки с соусом | E13: 154 | F13: 7.3 | G13: 2.7 | H13: 26.9 | I13: 2.62 | J13: 2.31 | K13: 1.99 | L13: Расчёт
A14: SF-D02-M05 | B14: 2 | C14: Ужин | D14: Паста с овощами | E14: 381 | F14: 15 | G14: 6.2 | H14: 68.8 | I14: 1.9 | J14: 1.67 | K14: 1.44 | L14: Расчёт
A15: SF-D03-M01 | B15: 3 | C15: Завтрак | D15: Омлет со шпинатом | E15: 340 | F15: 25.9 | G15: 17.7 | H15: 20.5 | I15: 3.47 | J15: 3.05 | K15: 2.63 | L15: Расчёт
A16: SF-D03-M02 | B16: 3 | C16: Второй завтрак | D16: Творог с ягодами | E16: 219 | F16: 23.1 | G16: 7.2 | H16: 17 | I16: 2.69 | J16: 2.37 | K16: 2.05 | L16: Расчёт
... A74: SF-D14-M05 | B74: 14 | C74: Ужин | D74: Индейка с овощами | E74: 379 | F74: 43.4 | G74: 9.3 | H74: 30.9 | I74: 6.1 | J74: 5.37 | K74: 4.63 | L74: Расчёт

Sheet Воронка продаж
A1: Воронка продаж и привлечение
A2: Покупатели рассчитываются от бюджета, стоимости заявки и доли заявок, которые доходят до первого заказа.
A4: Показатель | B4: М1 | C4: М2 | D4: М3 | E4: М4 | F4: М5 | G4: М6 | H4: М7 | I4: М8 | J4: М9 | K4: М10 | L4: М11 | M4: М12 | N4: М13 | O4: М14 | P4: М15 | Q4: М16 | R4: М17 | S4: М18 | T4: М19 | U4: М20 | V4: М21 | W4: М22 | X4: М23 | Y4: М24 | Z4: М25 | AA4: М26 | AB4: М27 | AC4: М28 | AD4: М29 | AE4: М30 | AF4: М31 | AG4: М32 | AH4: М33 | AI4: М34 | AJ4: М35 | AK4: М36 | AL4: Итого/среднее
A5: Рекламный бюджет | B5: 800 | C5: 1000 | D5: 1200 | E5: 1500 | F5: 1800 | G5: 2200 | H5: 2500 | I5: 2800 | J5: 3000 | K5: 3200 | L5: 3400 | M5: 3600 | N5: 3800 | O5: 3800 | P5: 3800 | Q5: 3800 | R5: 3800 | S5: 3800 | T5: 3800 | U5: 3800 | V5: 3800 | W5: 3800 | X5: 3800 | Y5: 3800 | Z5: 4200 | AA5: 4200 | AB5: 4200 | AC5: 4200 | AD5: 4200 | AE5: 4200 | AF5: 4200 | AG5: 4200 | AH5: 4200 | AI5: 4200 | AJ5: 4200 | AK5: 4200 | AL5: =SUM(B5:AK5) -> 123000
A6: Стоимость заявки | B6: =INDEX('Исходные данные'!$K$8:$K$29,MATCH("A14",'Исходные данные'!$J$8:$J$29,0)) -> 5.5 | C6: =INDEX('Исходные данные'!$K$8:$K$29,MATCH("A14",'Исходные данные'!$J$8:$J$29,0)) -> 5.5 | D6: =INDEX('Исходные данные'!$K$8:$K$29,MATCH("A14",'Исходные данные'!$J$8:$J$29,0)) -> 5.5 | E6: =INDEX('Исходные данные'!$K$8:$K$29,MATCH("A14",'Исходные данные'!$J$8:$J$29,0)) -> 5.5 | F6: =INDEX('Исходные данные'!$K$8:$K$29,MATCH("A14",'Исходные данные'!$J$8:$J$29,0)) -> 5.5 | G6: =INDEX('Исходные данные'!$K$8:$K$29,MATCH("A14",'Исходные данные'!$J$8:$J$29,0)) -> 5.5 | H6: =INDEX('Исходные данные'!$K$8:$K$29,MATCH("A14",'Исходные данные'!$J$8:$J$29,0)) -> 5.5 | I6: =INDEX('Исходные данные'!$K$8:$K$29,MATCH("A14",'Исходные данные'!$J$8:$J$29,0)) -> 5.5 | ... AK6: =INDEX('Исходные данные'!$K$8:$K$29,MATCH("A14",'Исходные данные'!$J$8:$J$29,0)) -> 5.5 | AL6: =AVERAGE(B6:AK6) -> 5.5
A7: Заявки из рекламы | B7: =B5/B6 -> 145.45455 | C7: =C5/C6 -> 181.81818 | D7: =D5/D6 -> 218.18182 | E7: =E5/E6 -> 272.72727 | F7: =F5/F6 -> 327.27273 | G7: =G5/G6 -> 400 | H7: =H5/H6 -> 454.54545 | I7: =I5/I6 -> 509.09091 | ... AK7: =AK5/AK6 -> 763.63636 | AL7: =SUM(B7:AK7) -> 22363.636
A8: Органические заявки | B8: 20 | C8: 24 | D8: 28 | E8: 32 | F8: 36 | G8: 40 | H8: 45 | I8: 50 | J8: 55 | K8: 60 | L8: 65 | M8: 70 | N8: 75 | O8: 75 | P8: 75 | Q8: 75 | R8: 75 | S8: 75 | T8: 75 | U8: 75 | V8: 75 | W8: 75 | X8: 75 | Y8: 75 | Z8: 85 | AA8: 85 | AB8: 85 | AC8: 85 | AD8: 85 | AE8: 85 | AF8: 85 | AG8: 85 | AH8: 85 | AI8: 85 | AJ8: 85 | AK8: 85 | AL8: =SUM(B8:AK8) -> 2445
A9: Всего заявок | B9: =SUM(B7:B8) -> 165.45455 | C9: =SUM(C7:C8) -> 205.81818 | D9: =SUM(D7:D8) -> 246.18182 | E9: =SUM(E7:E8) -> 304.72727 | F9: =SUM(F7:F8) -> 363.27273 | G9: =SUM(G7:G8) -> 440 | H9: =SUM(H7:H8) -> 499.54545 | I9: =SUM(I7:I8) -> 559.09091 | ... AK9: =SUM(AK7:AK8) -> 848.63636 | AL9: =SUM(B9:AK9) -> 24808.636
A10: Доля первого заказа | B10: =INDEX('Исходные данные'!$K$8:$K$29,MATCH("A15",'Исходные данные'!$J$8:$J$29,0)) -> 0.22 | C10: =INDEX('Исходные данные'!$K$8:$K$29,MATCH("A15",'Исходные данные'!$J$8:$J$29,0)) -> 0.22 | D10: =INDEX('Исходные данные'!$K$8:$K$29,MATCH("A15",'Исходные данные'!$J$8:$J$29,0)) -> 0.22 | E10: =INDEX('Исходные данные'!$K$8:$K$29,MATCH("A15",'Исходные данные'!$J$8:$J$29,0)) -> 0.22 | F10: =INDEX('Исходные данные'!$K$8:$K$29,MATCH("A15",'Исходные данные'!$J$8:$J$29,0)) -> 0.22 | G10: =INDEX('Исходные данные'!$K$8:$K$29,MATCH("A15",'Исходные данные'!$J$8:$J$29,0)) -> 0.22 | H10: =INDEX('Исходные данные'!$K$8:$K$29,MATCH("A15",'Исходные данные'!$J$8:$J$29,0)) -> 0.22 | I10: =INDEX('Исходные данные'!$K$8:$K$29,MATCH("A15",'Исходные данные'!$J$8:$J$29,0)) -> 0.22 | ... AK10: =INDEX('Исходные данные'!$K$8:$K$29,MATCH("A15",'Исходные данные'!$J$8:$J$29,0)) -> 0.22 | AL10: =AVERAGE(B10:AK10) -> 0.22
A11: Новые покупатели | B11: =B9*B10 -> 36.4 | C11: =C9*C10 -> 45.28 | D11: =D9*D10 -> 54.16 | E11: =E9*E10 -> 67.04 | F11: =F9*F10 -> 79.92 | G11: =G9*G10 -> 96.8 | H11: =H9*H10 -> 109.9 | I11: =I9*I10 -> 123 | ... AK11: =AK9*AK10 -> 186.7 | AL11: =SUM(B11:AK11) -> 5457.9
A12: Стоимость привлечения покупателя | B12: =B5/B11 -> 21.978022 | C12: =C5/C11 -> 22.084806 | D12: =D5/D11 -> 22.156573 | E12: =E5/E11 -> 22.374702 | F12: =F5/F11 -> 22.522523 | G12: =G5/G11 -> 22.727273 | H12: =H5/H11 -> 22.747953 | I12: =I5/I11 -> 22.764228 | ... AK12: =AK5/AK11 -> 22.495983 | AL12: =AVERAGE(B12:AK12) -> 22.514169
A13: Повтор 1-го месяца | B13: =INDEX('Исходные данные'!$K$8:$K$29,MATCH("A16",'Исходные данные'!$J$8:$J$29,0)) -> 0.4 | C13: =INDEX('Исходные данные'!$K$8:$K$29,MATCH("A16",'Исходные данные'!$J$8:$J$29,0)) -> 0.4 | D13: =INDEX('Исходные данные'!$K$8:$K$29,MATCH("A16",'Исходные данные'!$J$8:$J$29,0)) -> 0.4 | E13: =INDEX('Исходные данные'!$K$8:$K$29,MATCH("A16",'Исходные данные'!$J$8:$J$29,0)) -> 0.4 | F13: =INDEX('Исходные данные'!$K$8:$K$29,MATCH("A16",'Исходные данные'!$J$8:$J$29,0)) -> 0.4 | G13: =INDEX('Исходные данные'!$K$8:$K$29,MATCH("A16",'Исходные данные'!$J$8:$J$29,0)) -> 0.4 | H13: =INDEX('Исходные данные'!$K$8:$K$29,MATCH("A16",'Исходные данные'!$J$8:$J$29,0)) -> 0.4 | I13: =INDEX('Исходные данные'!$K$8:$K$29,MATCH("A16",'Исходные данные'!$J$8:$J$29,0)) -> 0.4 | ... AK13: =INDEX('Исходные данные'!$K$8:$K$29,MATCH("A16",'Исходные данные'!$J$8:$J$29,0)) -> 0.4 | AL13: =AVERAGE(B13:AK13) -> 0.4
A14: Повтор 2-го месяца | B14: =INDEX('Исходные данные'!$K$8:$K$29,MATCH("A17",'Исходные данные'!$J$8:$J$29,0)) -> 0.25 | C14: =INDEX('Исходные данные'!$K$8:$K$29,MATCH("A17",'Исходные данные'!$J$8:$J$29,0)) -> 0.25 | D14: =INDEX('Исходные данные'!$K$8:$K$29,MATCH("A17",'Исходные данные'!$J$8:$J$29,0)) -> 0.25 | E14: =INDEX('Исходные данные'!$K$8:$K$29,MATCH("A17",'Исходные данные'!$J$8:$J$29,0)) -> 0.25 | F14: =INDEX('Исходные данные'!$K$8:$K$29,MATCH("A17",'Исходные данные'!$J$8:$J$29,0)) -> 0.25 | G14: =INDEX('Исходные данные'!$K$8:$K$29,MATCH("A17",'Исходные данные'!$J$8:$J$29,0)) -> 0.25 | H14: =INDEX('Исходные данные'!$K$8:$K$29,MATCH("A17",'Исходные данные'!$J$8:$J$29,0)) -> 0.25 | I14: =INDEX('Исходные данные'!$K$8:$K$29,MATCH("A17",'Исходные данные'!$J$8:$J$29,0)) -> 0.25 | ... AK14: =INDEX('Исходные данные'!$K$8:$K$29,MATCH("A17",'Исходные данные'!$J$8:$J$29,0)) -> 0.25 | AL14: =AVERAGE(B14:AK14) -> 0.25
A15: Долгий повтор | B15: =INDEX('Исходные данные'!$K$8:$K$29,MATCH("A18",'Исходные данные'!$J$8:$J$29,0)) -> 0.15 | C15: =INDEX('Исходные данные'!$K$8:$K$29,MATCH("A18",'Исходные данные'!$J$8:$J$29,0)) -> 0.15 | D15: =INDEX('Исходные данные'!$K$8:$K$29,MATCH("A18",'Исходные данные'!$J$8:$J$29,0)) -> 0.15 | E15: =INDEX('Исходные данные'!$K$8:$K$29,MATCH("A18",'Исходные данные'!$J$8:$J$29,0)) -> 0.15 | F15: =INDEX('Исходные данные'!$K$8:$K$29,MATCH("A18",'Исходные данные'!$J$8:$J$29,0)) -> 0.15 | G15: =INDEX('Исходные данные'!$K$8:$K$29,MATCH("A18",'Исходные данные'!$J$8:$J$29,0)) -> 0.15 | H15: =INDEX('Исходные данные'!$K$8:$K$29,MATCH("A18",'Исходные данные'!$J$8:$J$29,0)) -> 0.15 | I15: =INDEX('Исходные данные'!$K$8:$K$29,MATCH("A18",'Исходные данные'!$J$8:$J$29,0)) -> 0.15 | ... AK15: =INDEX('Исходные данные'!$K$8:$K$29,MATCH("A18",'Исходные данные'!$J$8:$J$29,0)) -> 0.15 | AL15: =AVERAGE(B15:AK15) -> 0.15
A16: Активные покупатели | B16: =B11 -> 36.4 | C16: =C11+B11*C13 -> 59.84 | D16: =D11+C11*D13+B11*D14 -> 81.372 | E16: =E11+D11*E13+C11*E14+SUM(B11)*E15 -> 105.484 | F16: =F11+E11*F13+D11*F14+SUM(B11,C11)*F15 -> 132.528 | G16: =G11+F11*G13+E11*G14+SUM(B11,C11,D11)*G15 -> 165.904 | H16: =H11+G11*H13+F11*H14+SUM(B11,C11,D11,E11)*H15 -> 199.032 | I16: =I11+H11*I13+G11*I14+SUM(B11,C11,D11,E11,F11)*I15 -> 233.58 | J16: =J11+I11*J13+H11*J14+SUM(B11,C11,D11,E11,F11,G11)*J15 -> 265.715 | K16: =K11+J11*K13+I11*K14+SUM(B11,C11,D11,E11,F11,G11,H11)*K15 -> 298.215 | L16: =L11+K11*L13+J11*L14+SUM(B11,C11,D11,E11,F11,G11,H11,I11)*L15 -> 331.68 | M16: =M11+L11*M13+K11*M14+SUM(B11,C11,D11,E11,F11,G11,H11,I11,J11)*M15 -> 366.51 | N16: =N11+M11*N13+L11*N14+SUM(B11,C11,D11,E11,F11,G11,H11,I11,J11,K11)*N15 -> 402.705 | O16: =O11+N11*O13+M11*O14+SUM(B11,C11,D11,E11,F11,G11,H11,I11,J11,K11,L11)*O15 -> 431.165 | P16: =P11+O11*P13+N11*P14+SUM(B11,C11,D11,E11,F11,G11,H11,I11,J11,K11,L11,M11)*P15 -> 457.35 | Q16: =Q11+P11*Q13+O11*Q14+SUM(B11,C11,D11,E11,F11,G11,H11,I11,J11,K11,L11,M11,N11)*Q15 -> 482.625 | R16: =R11+Q11*R13+P11*R14+SUM(B11,C11,D11,E11,F11,G11,H11,I11,J11,K11,L11,M11,N11,O11)*R15 -> 507.9 | S16: =S11+R11*S13+Q11*S14+SUM(B11,C11,D11,E11,F11,G11,H11,I11,J11,K11,L11,M11,N11,O11,P11)*S15 -> 533.175 | T16: =T11+S11*T13+R11*T14+SUM(B11,C11,D11,E11,F11,G11,H11,I11,J11,K11,L11,M11,N11,O11,P11,Q11)*T15 -> 558.45 | U16: =U11+T11*U13+S11*U14+SUM(B11,C11,D11,E11,F11,G11,H11,I11,J11,K11,L11,M11,N11,O11,P11,Q11,R11)*U15 -> 583.725 | V16: =V11+U11*V13+T11*V14+SUM(B11,C11,D11,E11,F11,G11,H11,I11,J11,K11,L11,M11,N11,O11,P11,Q11,R11,S11)*V15 -> 609 | W16: =W11+V11*W13+U11*W14+SUM(B11,C11,D11,E11,F11,G11,H11,I11,J11,K11,L11,M11,N11,O11,P11,Q11,R11,S11,T11)*W15 -> 634.275 | X16: =X11+W11*X13+V11*X14+SUM(B11,C11,D11,E11,F11,G11,H11,I11,J11,K11,L11,M11,N11,O11,P11,Q11,R11,S11,T11,U11)*X15 -> 659.55 | Y16: =Y11+X11*Y13+W11*Y14+SUM(B11,C11,D11,E11,F11,G11,H11,I11,J11,K11,L11,M11,N11,O11,P11,Q11,R11,S11,T11,U11,V11)*Y15 -> 684.825 | Z16: =Z11+Y11*Z13+X11*Z14+SUM(B11,C11,D11,E11,F11,G11,H11,I11,J11,K11,L11,M11,N11,O11,P11,Q11,R11,S11,T11,U11,V11,W11)*Z15 -> 728.3 | AA16: =AA11+Z11*AA13+Y11*AA14+SUM(B11,C11,D11,E11,F11,G11,H11,I11,J11,K11,L11,M11,N11,O11,P11,Q11,R11,S11,T11,U11,V11,W11,X11)*AA15 -> 760.855 | AB16: =AB11+AA11*AB13+Z11*AB14+SUM(B11,C11,D11,E11,F11,G11,H11,I11,J11,K11,L11,M11,N11,O11,P11,Q11,R11,S11,T11,U11,V11,W11,X11,Y11)*AB15 -> 790.68 | AC16: =AC11+AB11*AC13+AA11*AC14+SUM(B11,C11,D11,E11,F11,G11,H11,I11,J11,K11,L11,M11,N11,O11,P11,Q11,R11,S11,T11,U11,V11,W11,X11,Y11,Z11)*AC15 -> 818.685 | AD16: =AD11+AC11*AD13+AB11*AD14+SUM(B11,C11,D11,E11,F11,G11,H11,I11,J11,K11,L11,M11,N11,O11,P11,Q11,R11,S11,T11,U11,V11,W11,X11,Y11,Z11,AA11)*AD15 -> 846.69 | AE16: =AE11+AD11*AE13+AC11*AE14+SUM(B11,C11,D11,E11,F11,G11,H11,I11,J11,K11,L11,M11,N11,O11,P11,Q11,R11,S11,T11,U11,V11,W11,X11,Y11,Z11,AA11,AB11)*AE15 -> 874.695 | AF16: =AF11+AE11*AF13+AD11*AF14+SUM(B11,C11,D11,E11,F11,G11,H11,I11,J11,K11,L11,M11,N11,O11,P11,Q11,R11,S11,T11,U11,V11,W11,X11,Y11,Z11,AA11,AB11,AC11)*AF15 -> 902.7 | AG16: =AG11+AF11*AG13+AE11*AG14+SUM(B11,C11,D11,E11,F11,G11,H11,I11,J11,K11,L11,M11,N11,O11,P11,Q11,R11,S11,T11,U11,V11,W11,X11,Y11,Z11,AA11,AB11,AC11,AD11)*AG15 -> 930.705 | AH16: =AH11+AG11*AH13+AF11*AH14+SUM(B11,C11,D11,E11,F11,G11,H11,I11,J11,K11,L11,M11,N11,O11,P11,Q11,R11,S11,T11,U11,V11,W11,X11,Y11,Z11,AA11,AB11,AC11,AD11,AE11)*AH15 -> 958.71 | AI16: =AI11+AH11*AI13+AG11*AI14+SUM(B11,C11,D11,E11,F11,G11,H11,I11,J11,K11,L11,M11,N11,O11,P11,Q11,R11,S11,T11,U11,V11,W11,X11,Y11,Z11,AA11,AB11,AC11,AD11,AE11,AF11)*AI15 -> 986.715 | AJ16: =AJ11+AI11*AJ13+AH11*AJ14+SUM(B11,C11,D11,E11,F11,G11,H11,I11,J11,K11,L11,M11,N11,O11,P11,Q11,R11,S11,T11,U11,V11,W11,X11,Y11,Z11,AA11,AB11,AC11,AD11,AE11,AF11,AG11)*AJ15 -> 1014.72 | AK16: =AK11+AJ11*AK13+AI11*AK14+SUM(B11,C11,D11,E11,F11,G11,H11,I11,J11,K11,L11,M11,N11,O11,P11,Q11,R11,S11,T11,U11,V11,W11,X11,Y11,Z11,AA11,AB11,AC11,AD11,AE11,AF11,AG11,AH11)*AK15 -> 1042.725 | AL16: =SUM(B16:AK16) -> 19477.185
A17: Дней на активного покупателя | B17: =INDEX('Исходные данные'!$K$8:$K$29,MATCH("A19",'Исходные данные'!$J$8:$J$29,0)) -> 5 | C17: =INDEX('Исходные данные'!$K$8:$K$29,MATCH("A19",'Исходные данные'!$J$8:$J$29,0)) -> 5 | D17: =INDEX('Исходные данные'!$K$8:$K$29,MATCH("A19",'Исходные данные'!$J$8:$J$29,0)) -> 5 | E17: =INDEX('Исходные данные'!$K$8:$K$29,MATCH("A19",'Исходные данные'!$J$8:$J$29,0)) -> 5 | F17: =INDEX('Исходные данные'!$K$8:$K$29,MATCH("A19",'Исходные данные'!$J$8:$J$29,0)) -> 5 | G17: =INDEX('Исходные данные'!$K$8:$K$29,MATCH("A19",'Исходные данные'!$J$8:$J$29,0)) -> 5 | H17: =INDEX('Исходные данные'!$K$8:$K$29,MATCH("A19",'Исходные данные'!$J$8:$J$29,0)) -> 5 | I17: =INDEX('Исходные данные'!$K$8:$K$29,MATCH("A19",'Исходные данные'!$J$8:$J$29,0)) -> 5 | ... AK17: =INDEX('Исходные данные'!$K$8:$K$29,MATCH("A19",'Исходные данные'!$J$8:$J$29,0)) -> 5 | AL17: =AVERAGE(B17:AK17) -> 5
A18: Спрос, рацион-дней | B18: =B16*B17 -> 182 | C18: =C16*C17 -> 299.2 | D18: =D16*D17 -> 406.86 | E18: =E16*E17 -> 527.42 | F18: =F16*F17 -> 662.64 | G18: =G16*G17 -> 829.52 | H18: =H16*H17 -> 995.16 | I18: =I16*I17 -> 1167.9 | ... AK18: =AK16*AK17 -> 5213.625 | AL18: =SUM(B18:AK18) -> 97385.925

Sheet План 36 месяцев
A1: План работы на 36 месяцев
A2: Объём ограничивается спросом и мощностью кухни. Переменные расходы снижаются по мере роста партии.
A4: Показатель | B4: М1 | C4: М2 | D4: М3 | E4: М4 | F4: М5 | G4: М6 | H4: М7 | I4: М8 | J4: М9 | K4: М10 | L4: М11 | M4: М12 | N4: М13 | O4: М14 | P4: М15 | Q4: М16 | R4: М17 | S4: М18 | T4: М19 | U4: М20 | V4: М21 | W4: М22 | X4: М23 | Y4: М24 | Z4: М25 | AA4: М26 | AB4: М27 | AC4: М28 | AD4: М29 | AE4: М30 | AF4: М31 | AG4: М32 | AH4: М33 | AI4: М34 | AJ4: М35 | AK4: М36 | AL4: Итого/среднее
A5: Рабочих дней | B5: =INDEX('Исходные данные'!$K$8:$K$29,MATCH("A20",'Исходные данные'!$J$8:$J$29,0)) -> 26 | C5: =INDEX('Исходные данные'!$K$8:$K$29,MATCH("A20",'Исходные данные'!$J$8:$J$29,0)) -> 26 | D5: =INDEX('Исходные данные'!$K$8:$K$29,MATCH("A20",'Исходные данные'!$J$8:$J$29,0)) -> 26 | E5: =INDEX('Исходные данные'!$K$8:$K$29,MATCH("A20",'Исходные данные'!$J$8:$J$29,0)) -> 26 | F5: =INDEX('Исходные данные'!$K$8:$K$29,MATCH("A20",'Исходные данные'!$J$8:$J$29,0)) -> 26 | G5: =INDEX('Исходные данные'!$K$8:$K$29,MATCH("A20",'Исходные данные'!$J$8:$J$29,0)) -> 26 | H5: =INDEX('Исходные данные'!$K$8:$K$29,MATCH("A20",'Исходные данные'!$J$8:$J$29,0)) -> 26 | I5: =INDEX('Исходные данные'!$K$8:$K$29,MATCH("A20",'Исходные данные'!$J$8:$J$29,0)) -> 26 | ... AK5: =INDEX('Исходные данные'!$K$8:$K$29,MATCH("A20",'Исходные данные'!$J$8:$J$29,0)) -> 26 | AL5: =AVERAGE(B5:AK5) -> 26
A6: Мощность в день | B6: 20 | C6: 25 | D6: 30 | E6: 35 | F6: 40 | G6: 45 | H6: 50 | I6: 55 | J6: 60 | K6: 65 | L6: 70 | M6: 75 | N6: 75 | O6: 80 | P6: 80 | Q6: 85 | R6: 85 | S6: 90 | T6: 90 | U6: 95 | V6: 95 | W6: 100 | X6: 100 | Y6: 105 | Z6: 105 | AA6: 110 | AB6: 110 | AC6: 115 | AD6: 115 | AE6: 120 | AF6: 120 | AG6: 120 | AH6: 120 | AI6: 120 | AJ6: 120 | AK6: 120 | AL6: =AVERAGE(B6:AK6) -> 84.583333
A7: Максимальный объём | B7: =B5*B6 -> 520 | C7: =C5*C6 -> 650 | D7: =D5*D6 -> 780 | E7: =E5*E6 -> 910 | F7: =F5*F6 -> 1040 | G7: =G5*G6 -> 1170 | H7: =H5*H6 -> 1300 | I7: =I5*I6 -> 1430 | ... AK7: =AK5*AK6 -> 3120 | AL7: =SUM(B7:AK7) -> 79170
A8: Спрос из воронки | B8: ='Воронка продаж'!B18 -> 182 | C8: ='Воронка продаж'!C18 -> 299.2 | D8: ='Воронка продаж'!D18 -> 406.86 | E8: ='Воронка продаж'!E18 -> 527.42 | F8: ='Воронка продаж'!F18 -> 662.64 | G8: ='Воронка продаж'!G18 -> 829.52 | H8: ='Воронка продаж'!H18 -> 995.16 | I8: ='Воронка продаж'!I18 -> 1167.9 | ... AK8: ='Воронка продаж'!AK18 -> 5213.625 | AL8: =SUM(B8:AK8) -> 97385.925
A9: Доставлено рацион-дней | B9: =MIN(B7,B8) -> 182 | C9: =MIN(C7,C8) -> 299.2 | D9: =MIN(D7,D8) -> 406.86 | E9: =MIN(E7,E8) -> 527.42 | F9: =MIN(F7,F8) -> 662.64 | G9: =MIN(G7,G8) -> 829.52 | H9: =MIN(H7,H8) -> 995.16 | I9: =MIN(I7,I8) -> 1167.9 | ... AK9: =MIN(AK7,AK8) -> 3120 | AL9: =SUM(B9:AK9) -> 75731.3
A10: Средняя цена | B10: =INDEX('Исходные данные'!$K$8:$K$29,MATCH("A01",'Исходные данные'!$J$8:$J$29,0)) -> 44.35 | C10: =INDEX('Исходные данные'!$K$8:$K$29,MATCH("A01",'Исходные данные'!$J$8:$J$29,0)) -> 44.35 | D10: =INDEX('Исходные данные'!$K$8:$K$29,MATCH("A01",'Исходные данные'!$J$8:$J$29,0)) -> 44.35 | E10: =INDEX('Исходные данные'!$K$8:$K$29,MATCH("A01",'Исходные данные'!$J$8:$J$29,0)) -> 44.35 | F10: =INDEX('Исходные данные'!$K$8:$K$29,MATCH("A01",'Исходные данные'!$J$8:$J$29,0)) -> 44.35 | G10: =INDEX('Исходные данные'!$K$8:$K$29,MATCH("A01",'Исходные данные'!$J$8:$J$29,0)) -> 44.35 | H10: =INDEX('Исходные данные'!$K$8:$K$29,MATCH("A01",'Исходные данные'!$J$8:$J$29,0)) -> 44.35 | I10: =INDEX('Исходные данные'!$K$8:$K$29,MATCH("A01",'Исходные данные'!$J$8:$J$29,0)) -> 44.35 | ... AK10: =INDEX('Исходные данные'!$K$8:$K$29,MATCH("A01",'Исходные данные'!$J$8:$J$29,0)) -> 44.35 | AL10: =AVERAGE(B10:AK10) -> 44.35
A11: Выручка | B11: =B9*B10 -> 8071.7 | C11: =C9*C10 -> 13269.52 | D11: =D9*D10 -> 18044.241 | E11: =E9*E10 -> 23391.077 | F11: =F9*F10 -> 29388.084 | G11: =G9*G10 -> 36789.212 | H11: =H9*H10 -> 44135.346 | I11: =I9*I10 -> 51796.365 | ... AK11: =AK9*AK10 -> 138372 | AL11: =SUM(B11:AK11) -> 3358683.2
A12: Переменные расходы на день | B12: =IF(B16<40,'Экономика дня'!$B$14,'Экономика дня'!$C$14) -> 30.2098 | C12: =IF(C16<40,'Экономика дня'!$B$14,'Экономика дня'!$C$14) -> 30.2098 | D12: =IF(D16<40,'Экономика дня'!$B$14,'Экономика дня'!$C$14) -> 30.2098 | E12: =IF(E16<40,'Экономика дня'!$B$14,'Экономика дня'!$C$14) -> 30.2098 | F12: =IF(F16<40,'Экономика дня'!$B$14,'Экономика дня'!$C$14) -> 30.2098 | G12: =IF(G16<40,'Экономика дня'!$B$14,'Экономика дня'!$C$14) -> 30.2098 | H12: =IF(H16<40,'Экономика дня'!$B$14,'Экономика дня'!$C$14) -> 30.2098 | I12: =IF(I16<40,'Экономика дня'!$B$14,'Экономика дня'!$C$14) -> 30.2098 | ... AK12: =IF(AK16<40,'Экономика дня'!$B$14,'Экономика дня'!$C$14) -> 30.2098 | AL12: =AVERAGE(B12:AK12) -> 30.2098
A13: Переменные расходы | B13: =B9*B12 -> 5498.1836 | C13: =C9*C12 -> 9038.7722 | D13: =D9*D12 -> 12291.159 | E13: =E9*E12 -> 15933.253 | F13: =F9*F12 -> 20018.222 | G13: =G9*G12 -> 25059.633 | H13: =H9*H12 -> 30063.585 | I13: =I9*I12 -> 35282.025 | ... AK13: =AK9*AK12 -> 94254.576 | AL13: =SUM(B13:AK13) -> 2287827.4
A14: Вклад на покрытие | B14: =B11-B13 -> 2573.5164 | C14: =C11-C13 -> 4230.7478 | D14: =D11-D13 -> 5753.0818 | E14: =E11-E13 -> 7457.8243 | F14: =F11-F13 -> 9369.8621 | G14: =G11-G13 -> 11729.579 | H14: =H11-H13 -> 14071.761 | I14: =I11-I13 -> 16514.34 | ... AK14: =AK11-AK13 -> 44117.424 | AL14: =SUM(B14:AK14) -> 1070855.7
A15: Маржа вклада | B15: =B14/B11 -> 0.31883202 | C15: =C14/C11 -> 0.31883202 | D15: =D14/D11 -> 0.31883202 | E15: =E14/E11 -> 0.31883202 | F15: =F14/F11 -> 0.31883202 | G15: =G14/G11 -> 0.31883202 | H15: =H14/H11 -> 0.31883202 | I15: =I14/I11 -> 0.31883202 | ... AK15: =AK14/AK11 -> 0.31883202 | AL15: =AVERAGE(B15:AK15) -> 0.31883202
A16: Постоянные расходы | B16: 7000 | C16: 7000 | D16: 7000 | E16: 9000 | F16: 9000 | G16: 9000 | H16: 12000 | I16: 12000 | J16: 12000 | K16: 12000 | L16: 12000 | M16: 12000 | N16: 15000 | O16: 15000 | P16: 15000 | Q16: 15000 | R16: 15000 | S16: 15000 | T16: 15000 | U16: 15000 | V16: 15000 | W16: 15000 | X16: 15000 | Y16: 15000 | Z16: 18000 | AA16: 18000 | AB16: 18000 | AC16: 18000 | AD16: 18000 | AE16: 18000 | AF16: 18000 | AG16: 18000 | AH16: 18000 | AI16: 18000 | AJ16: 18000 | AK16: 18000 | AL16: =SUM(B16:AK16) -> 516000
A17: Реклама | B17: ='Воронка продаж'!B5 -> 800 | C17: ='Воронка продаж'!C5 -> 1000 | D17: ='Воронка продаж'!D5 -> 1200 | E17: ='Воронка продаж'!E5 -> 1500 | F17: ='Воронка продаж'!F5 -> 1800 | G17: ='Воронка продаж'!G5 -> 2200 | H17: ='Воронка продаж'!H5 -> 2500 | I17: ='Воронка продаж'!I5 -> 2800 | ... AK17: ='Воронка продаж'!AK5 -> 4200 | AL17: =SUM(B17:AK17) -> 123000
A18: Операционный результат | B18: =B14-B16-B17 -> -5226.4836 | C18: =C14-C16-C17 -> -3769.2522 | D18: =D14-D16-D17 -> -2446.9182 | E18: =E14-E16-E17 -> -3042.1757 | F18: =F14-F16-F17 -> -1430.1379 | G18: =G14-G16-G17 -> 529.5787 | H18: =H14-H16-H17 -> -428.23857 | I18: =I14-I16-I17 -> 1714.3396 | ... AK18: =AK14-AK16-AK17 -> 21917.424 | AL18: =SUM(B18:AK18) -> 431855.73
A19: Операционная рентабельность | B19: =B18/B11 -> -0.64750717 | C19: =C18/C11 -> -0.28405339 | D19: =D18/D11 -> -0.1356066 | E19: =E18/E11 -> -0.1300571 | F19: =F18/F11 -> -0.048663869 | G19: =G18/G11 -> 0.014394946 | H19: =H18/H11 -> -0.0097028483 | I19: =I18/I11 -> 0.033097681 | ... AK19: =AK18/AK11 -> 0.15839494 | AL19: =AVERAGE(B19:AK19) -> 0.073518276
A20: Средний объём в день | B20: =B9/B5 -> 7 | C20: =C9/C5 -> 11.507692 | D20: =D9/D5 -> 15.648462 | E20: =E9/E5 -> 20.285385 | F20: =F9/F5 -> 25.486154 | G20: =G9/G5 -> 31.904615 | H20: =H9/H5 -> 38.275385 | I20: =I9/I5 -> 44.919231 | ... AK20: =AK9/AK5 -> 120 | AL20: =AVERAGE(B20:AK20) -> 80.909509

Sheet Движение денег
A1: Движение денежных средств
A2: Показывает фактическую потребность в финансировании и запас денег.
A4: Показатель | B4: М1 | C4: М2 | D4: М3 | E4: М4 | F4: М5 | G4: М6 | H4: М7 | I4: М8 | J4: М9 | K4: М10 | L4: М11 | M4: М12 | N4: М13 | O4: М14 | P4: М15 | Q4: М16 | R4: М17 | S4: М18 | T4: М19 | U4: М20 | V4: М21 | W4: М22 | X4: М23 | Y4: М24 | Z4: М25 | AA4: М26 | AB4: М27 | AC4: М28 | AD4: М29 | AE4: М30 | AF4: М31 | AG4: М32 | AH4: М33 | AI4: М34 | AJ4: М35 | AK4: М36 | AL4: Итого/конец
A5: Остаток на начало | B5: 0 | C5: =B16 -> 10531.365 | D5: =C16 -> 18606.179 | E5: =D16 -> 10016.019 | F5: =E16 -> 22813.438 | G5: =F16 -> 19203.39 | H5: =G16 -> 18010.935 | I5: =H16 -> 17362.312 | J5: =I16 -> 18846.821 | ... AK5: =AJ16 -> 440287.14 | AL5: =AK5 -> 440287.14
A6: Выручка | B6: ='План 36 месяцев'!B11 -> 8071.7 | C6: ='План 36 месяцев'!C11 -> 13269.52 | D6: ='План 36 месяцев'!D11 -> 18044.241 | E6: ='План 36 месяцев'!E11 -> 23391.077 | F6: ='План 36 месяцев'!F11 -> 29388.084 | G6: ='План 36 месяцев'!G11 -> 36789.212 | H6: ='План 36 месяцев'!H11 -> 44135.346 | I6: ='План 36 месяцев'!I11 -> 51796.365 | ... AK6: ='План 36 месяцев'!AK11 -> 138372 | AL6: =SUM(B6:AK6) -> 3358683.2
A7: Финансирование | B7: 28000 | C7: 20000 | D7: 0 | E7: 20000 | F7: 0 | G7: 0 | H7: 0 | I7: 0 | J7: 0 | K7: 0 | L7: 0 | M7: 0 | N7: 0 | O7: 0 | P7: 0 | Q7: 0 | R7: 0 | S7: 0 | T7: 0 | U7: 0 | V7: 0 | W7: 0 | X7: 0 | Y7: 0 | Z7: 0 | AA7: 0 | AB7: 0 | AC7: 0 | AD7: 0 | AE7: 0 | AF7: 0 | AG7: 0 | AH7: 0 | AI7: 0 | AJ7: 0 | AK7: 0 | AL7: =SUM(B7:AK7) -> 68000
A8: Всего поступило | B8: =SUM(B6:B7) -> 36071.7 | C8: =SUM(C6:C7) -> 33269.52 | D8: =SUM(D6:D7) -> 18044.241 | E8: =SUM(E6:E7) -> 43391.077 | F8: =SUM(F6:F7) -> 29388.084 | G8: =SUM(G6:G7) -> 36789.212 | H8: =SUM(H6:H7) -> 44135.346 | I8: =SUM(I6:I7) -> 51796.365 | ... AK8: =SUM(AK6:AK7) -> 138372 | AL8: =SUM(B8:AK8) -> 3426683.2
A9: Переменные расходы | B9: ='План 36 месяцев'!B13 -> 5498.1836 | C9: ='План 36 месяцев'!C13 -> 9038.7722 | D9: ='План 36 месяцев'!D13 -> 12291.159 | E9: ='План 36 месяцев'!E13 -> 15933.253 | F9: ='План 36 месяцев'!F13 -> 20018.222 | G9: ='План 36 месяцев'!G13 -> 25059.633 | H9: ='План 36 месяцев'!H13 -> 30063.585 | I9: ='План 36 месяцев'!I13 -> 35282.025 | ... AK9: ='План 36 месяцев'!AK13 -> 94254.576 | AL9: =SUM(B9:AK9) -> 2287827.4
A10: Постоянные расходы | B10: ='План 36 месяцев'!B16 -> 7000 | C10: ='План 36 месяцев'!C16 -> 7000 | D10: ='План 36 месяцев'!D16 -> 7000 | E10: ='План 36 месяцев'!E16 -> 9000 | F10: ='План 36 месяцев'!F16 -> 9000 | G10: ='План 36 месяцев'!G16 -> 9000 | H10: ='План 36 месяцев'!H16 -> 12000 | I10: ='План 36 месяцев'!I16 -> 12000 | ... AK10: ='План 36 месяцев'!AK16 -> 18000 | AL10: =SUM(B10:AK10) -> 516000
A11: Реклама | B11: ='План 36 месяцев'!B17 -> 800 | C11: ='План 36 месяцев'!C17 -> 1000 | D11: ='План 36 месяцев'!D17 -> 1200 | E11: ='План 36 месяцев'!E17 -> 1500 | F11: ='План 36 месяцев'!F17 -> 1800 | G11: ='План 36 месяцев'!G17 -> 2200 | H11: ='План 36 месяцев'!H17 -> 2500 | I11: ='План 36 месяцев'!I17 -> 2800 | ... AK11: ='План 36 месяцев'!AK17 -> 4200 | AL11: =SUM(B11:AK11) -> 123000
A12: Разовые расходы запуска | B12: 12000 | C12: 8000 | D12: 6000 | E12: 4000 | F12: 2000 | G12: 1500 | H12: 0 | I12: 0 | J12: 0 | K12: 0 | L12: 0 | M12: 0 | N12: 0 | O12: 0 | P12: 0 | Q12: 0 | R12: 0 | S12: 0 | T12: 0 | U12: 0 | V12: 0 | W12: 0 | X12: 0 | Y12: 0 | Z12: 0 | AA12: 0 | AB12: 0 | AC12: 0 | AD12: 0 | AE12: 0 | AF12: 0 | AG12: 0 | AH12: 0 | AI12: 0 | AJ12: 0 | AK12: 0 | AL12: =SUM(B12:AK12) -> 33500
A13: Изменение оборотного капитала | B13: =IF(B6>0,B6*3%-0,0) -> 242.151 | C13: =IF(C6>0,C6*3%-B6*3%,0) -> 155.9346 | D13: =IF(D6>0,D6*3%-C6*3%,0) -> 143.24163 | E13: =IF(E6>0,E6*3%-D6*3%,0) -> 160.40508 | F13: =IF(F6>0,F6*3%-E6*3%,0) -> 179.91021 | G13: =IF(G6>0,G6*3%-F6*3%,0) -> 222.03384 | H13: =IF(H6>0,H6*3%-G6*3%,0) -> 220.38402 | I13: =IF(I6>0,I6*3%-H6*3%,0) -> 229.83057 | J13: =IF(J6>0,J6*3%-I6*3%,0) -> 213.77809 | ... AK13: =IF(AK6>0,AK6*3%-AJ6*3%,0) -> 0 | AL13: =SUM(B13:AK13) -> 4151.16
A14: Всего потрачено | B14: =SUM(B9:B13) -> 25540.335 | C14: =SUM(C9:C13) -> 25194.707 | D14: =SUM(D9:D13) -> 26634.401 | E14: =SUM(E9:E13) -> 30593.658 | F14: =SUM(F9:F13) -> 32998.132 | G14: =SUM(G9:G13) -> 37981.667 | H14: =SUM(H9:H13) -> 44783.969 | I14: =SUM(I9:I13) -> 50311.856 | ... AK14: =SUM(AK9:AK13) -> 116454.58 | AL14: =SUM(B14:AK14) -> 2964478.6
A15: Чистое движение | B15: =B8-B14 -> 10531.365 | C15: =C8-C14 -> 8074.8132 | D15: =D8-D14 -> -8590.1599 | E15: =E8-E14 -> 12797.419 | F15: =F8-F14 -> -3610.0481 | G15: =G8-G14 -> -1192.4551 | H15: =H8-H14 -> -648.62259 | I15: =I8-I14 -> 1484.509 | ... AK15: =AK8-AK14 -> 21917.424 | AL15: =SUM(B15:AK15) -> 462204.57
A16: Остаток на конец | B16: =B5+B15 -> 10531.365 | C16: =C5+C15 -> 18606.179 | D16: =D5+D15 -> 10016.019 | E16: =E5+E15 -> 22813.438 | F16: =F5+F15 -> 19203.39 | G16: =G5+G15 -> 18010.935 | H16: =H5+H15 -> 17362.312 | I16: =I5+I15 -> 18846.821 | ... AK16: =AK5+AK15 -> 462204.57 | AL16: =AK16 -> 462204.57
A17: Целевой резерв | B17: =INDEX('Исходные данные'!$K$8:$K$29,MATCH("A22",'Исходные данные'!$J$8:$J$29,0)) -> 10000 | C17: =INDEX('Исходные данные'!$K$8:$K$29,MATCH("A22",'Исходные данные'!$J$8:$J$29,0)) -> 10000 | D17: =INDEX('Исходные данные'!$K$8:$K$29,MATCH("A22",'Исходные данные'!$J$8:$J$29,0)) -> 10000 | E17: =INDEX('Исходные данные'!$K$8:$K$29,MATCH("A22",'Исходные данные'!$J$8:$J$29,0)) -> 10000 | F17: =INDEX('Исходные данные'!$K$8:$K$29,MATCH("A22",'Исходные данные'!$J$8:$J$29,0)) -> 10000 | G17: =INDEX('Исходные данные'!$K$8:$K$29,MATCH("A22",'Исходные данные'!$J$8:$J$29,0)) -> 10000 | H17: =INDEX('Исходные данные'!$K$8:$K$29,MATCH("A22",'Исходные данные'!$J$8:$J$29,0)) -> 10000 | I17: =INDEX('Исходные данные'!$K$8:$K$29,MATCH("A22",'Исходные данные'!$J$8:$J$29,0)) -> 10000 | ... AK17: =INDEX('Исходные данные'!$K$8:$K$29,MATCH("A22",'Исходные данные'!$J$8:$J$29,0)) -> 10000 | AL17: =AK17 -> 10000
A18: Запас сверх резерва | B18: =B16-B17 -> 531.3654 | C18: =C16-C17 -> 8606.1786 | D18: =D16-D17 -> 16.018782 | E18: =E16-E17 -> 12813.438 | F18: =F16-F17 -> 9203.3899 | G18: =G16-G17 -> 8010.9348 | H18: =H16-H17 -> 7362.3122 | I18: =I16-I17 -> 8846.8212 | ... AK18: =AK16-AK17 -> 452204.57 | AL18: =AK18 -> 452204.57

Sheet Первые 13 недель
A1: Первые 13 недель
A2: Недельный контроль продаж, затрат и денег на этапе пилота.
A4: Показатель | B4: Неделя 1 | C4: Неделя 2 | D4: Неделя 3 | E4: Неделя 4 | F4: Неделя 5 | G4: Неделя 6 | H4: Неделя 7 | I4: Неделя 8 | J4: Неделя 9 | K4: Неделя 10 | L4: Неделя 11 | M4: Неделя 12 | N4: Неделя 13 | O4: Итого/конец
A5: Рацион-дней | B5: 0 | C5: 0 | D5: 40 | E5: 60 | F5: 80 | G5: 100 | H5: 120 | I5: 140 | J5: 160 | K5: 180 | L5: 200 | M5: 220 | N5: 240 | O5: =SUM(B5:N5) -> 1540
A6: Средняя цена | B6: =INDEX('Исходные данные'!$K$8:$K$29,MATCH("A01",'Исходные данные'!$J$8:$J$29,0)) -> 44.35 | C6: =INDEX('Исходные данные'!$K$8:$K$29,MATCH("A01",'Исходные данные'!$J$8:$J$29,0)) -> 44.35 | D6: =INDEX('Исходные данные'!$K$8:$K$29,MATCH("A01",'Исходные данные'!$J$8:$J$29,0)) -> 44.35 | E6: =INDEX('Исходные данные'!$K$8:$K$29,MATCH("A01",'Исходные данные'!$J$8:$J$29,0)) -> 44.35 | F6: =INDEX('Исходные данные'!$K$8:$K$29,MATCH("A01",'Исходные данные'!$J$8:$J$29,0)) -> 44.35 | G6: =INDEX('Исходные данные'!$K$8:$K$29,MATCH("A01",'Исходные данные'!$J$8:$J$29,0)) -> 44.35 | H6: =INDEX('Исходные данные'!$K$8:$K$29,MATCH("A01",'Исходные данные'!$J$8:$J$29,0)) -> 44.35 | I6: =INDEX('Исходные данные'!$K$8:$K$29,MATCH("A01",'Исходные данные'!$J$8:$J$29,0)) -> 44.35 | ... N6: =INDEX('Исходные данные'!$K$8:$K$29,MATCH("A01",'Исходные данные'!$J$8:$J$29,0)) -> 44.35 | O6: =SUM(B6:N6) -> 576.55
A7: Выручка | B7: =B5*B6 -> 0 | C7: =C5*C6 -> 0 | D7: =D5*D6 -> 1774 | E7: =E5*E6 -> 2661 | F7: =F5*F6 -> 3548 | G7: =G5*G6 -> 4435 | H7: =H5*H6 -> 5322 | I7: =I5*I6 -> 6209 | ... N7: =N5*N6 -> 10644 | O7: =SUM(B7:N7) -> 68299
A8: Переменные расходы на день | B8: ='Экономика дня'!$B$14 -> 34.4228 | C8: ='Экономика дня'!$B$14 -> 34.4228 | D8: ='Экономика дня'!$B$14 -> 34.4228 | E8: ='Экономика дня'!$B$14 -> 34.4228 | F8: ='Экономика дня'!$B$14 -> 34.4228 | G8: ='Экономика дня'!$B$14 -> 34.4228 | H8: ='Экономика дня'!$B$14 -> 34.4228 | I8: ='Экономика дня'!$B$14 -> 34.4228 | J8: ='Экономика дня'!$C$14 -> 30.2098 | K8: ='Экономика дня'!$C$14 -> 30.2098 | L8: ='Экономика дня'!$C$14 -> 30.2098 | M8: ='Экономика дня'!$C$14 -> 30.2098 | N8: ='Экономика дня'!$C$14 -> 30.2098 | O8: =SUM(B8:N8) -> 426.4314
A9: Переменные расходы | B9: =B5*B8 -> 0 | C9: =C5*C8 -> 0 | D9: =D5*D8 -> 1376.912 | E9: =E5*E8 -> 2065.368 | F9: =F5*F8 -> 2753.824 | G9: =G5*G8 -> 3442.28 | H9: =H5*H8 -> 4130.736 | I9: =I5*I8 -> 4819.192 | ... N9: =N5*N8 -> 7250.352 | O9: =SUM(B9:N9) -> 48798.112
A10: Постоянные расходы | B10: 1750 | C10: 1750 | D10: 1750 | E10: 1750 | F10: 1750 | G10: 1750 | H10: 1750 | I10: 1750 | J10: 1750 | K10: 1750 | L10: 1750 | M10: 1750 | N10: 1750 | O10: =SUM(B10:N10) -> 22750
A11: Реклама | B11: 0 | C11: 0 | D11: 800 | E11: 800 | F11: 1000 | G11: 1000 | H11: 1200 | I11: 1200 | J11: 1400 | K11: 1400 | L11: 1600 | M11: 1600 | N11: 1800 | O11: =SUM(B11:N11) -> 13800
A12: Разовые расходы | B12: 9000 | C12: 6000 | D12: 4000 | E12: 2500 | F12: 1500 | G12: 1000 | H12: 0 | I12: 0 | J12: 0 | K12: 0 | L12: 0 | M12: 0 | N12: 0 | O12: =SUM(B12:N12) -> 24000
A13: Финансирование | B13: 28000 | C13: 0 | D13: 20000 | E13: 0 | F13: 0 | G13: 0 | H13: 20000 | I13: 0 | J13: 0 | K13: 0 | L13: 0 | M13: 0 | N13: 0 | O13: =SUM(B13:N13) -> 68000
A14: Чистое движение | B14: =B7+B13-SUM(B9:B12) -> 17250 | C14: =C7+C13-SUM(C9:C12) -> -7750 | D14: =D7+D13-SUM(D9:D12) -> 13847.088 | E14: =E7+E13-SUM(E9:E12) -> -4454.368 | F14: =F7+F13-SUM(F9:F12) -> -3455.824 | G14: =G7+G13-SUM(G9:G12) -> -2757.28 | H14: =H7+H13-SUM(H9:H12) -> 18241.264 | I14: =I7+I13-SUM(I9:I12) -> -1560.192 | ... N14: =N7+N13-SUM(N9:N12) -> -156.352 | O14: =SUM(B14:N14) -> 26950.888
A15: Остаток на конец | B15: =B14 -> 17250 | C15: =B15+C14 -> 9500 | D15: =C15+D14 -> 23347.088 | E15: =D15+E14 -> 18892.72 | F15: =E15+F14 -> 15436.896 | G15: =F15+G14 -> 12679.616 | H15: =G15+H14 -> 30920.88 | I15: =H15+I14 -> 29360.688 | J15: =I15+J14 -> 28473.12 | ... N15: =M15+N14 -> 26950.888 | O15: =N15 -> 26950.888

Sheet Потребность в деньгах
A1: Потребность в финансировании
A2: Каждая статья привязана к конкретному результату.
A4: Статья | B4: Сумма | C4: Доля | D4: Зачем нужна | E4: Результат | F4: Этап
A5: Технологическая и производственная подготовка | B5: 8200 | C5: =B5/$B$13 -> 0.12058824 | D5: Проработка 70 карт, контрольные готовки, расчёт выходов, пищевой ценности, аллергенов и маркировки. | E5: Утверждённое меню и воспроизводимый производственный процесс. | F5: Подготовка
A6: Запуск кухни и первая партия | B6: 7600 | C6: =B6/$B$13 -> 0.11176471 | D6: Депозит кухни, тестовая смена, санитарные материалы, первая закупка сырья. | E6: Рабочая производственная площадка и первый контролируемый выпуск. | F6: Подготовка
A7: Упаковка и маркировка | B7: 4800 | C7: =B7/$B$13 -> 0.070588235 | D7: Контейнеры, крафт-короб, этикетки, термопринтер/расходники, транспортные тесты. | E7: Готовая упаковочная система на пилот. | F7: Подготовка
A8: Логистика и холодовая цепь | B8: 3200 | C8: =B8/$B$13 -> 0.047058824 | D8: Термосумки, термометры, маршрутные тесты, резерв на курьерскую доставку. | E8: Подтверждённый маршрут и контроль температуры. | F8: Подготовка
A9: Продвижение и продажи | B9: 8500 | C9: =B9/$B$13 -> 0.125 | D9: Фотосъёмка фактического продукта, рекламные тесты, партнёрские размещения, печатные материалы. | E9: Измеримый поток заявок и первые оплаченные клиенты. | F9: Пилот
A10: Оборотный капитал | B10: 20500 | C10: =B10/$B$13 -> 0.30147059 | D10: Сырьё, кухня, упаковка, доставка и текущие расходы в период набора объёма. | E10: Непрерывная работа до выхода на операционную безубыточность. | F10: Пилот
A11: Правовой, бухгалтерский и платёжный контур | B11: 2600 | C11: =B11/$B$13 -> 0.038235294 | D11: Регистрация/договоры, бухгалтерская настройка, платёжный сервис, кассовый контур. | E11: Возможность законно принимать оплату и оформлять документы. | F11: Пилот
A12: Резерв | B12: 12600 | C12: =B12/$B$13 -> 0.18529412 | D12: Отклонения цен, повторные тесты и непредвиденные расходы. | E12: Запас устойчивости без остановки пилота. | F12: Пилот
A13: ИТОГО | B13: =SUM(B5:B12) -> 68000 | C13: =100% -> 1

Sheet Чувствительность
A1: Что быстрее всего ломает экономику
A2: Расчёт при устойчивом объёме 60 рационов в день и 26 рабочих днях.
A4: Сценарий | B4: Цена | C4: Сырьё | D4: Кухня | E4: Упаковка | F4: Доставка | G4: Вклад/день | H4: Результат/месяц | I4: Вывод
A5: Основной | B5: ='Экономика дня'!C5*(1+0) -> 44.35 | C5: ='Экономика дня'!C6*(1+0) -> 13.35 | D5: ='Экономика дня'!C7*(1+0) -> 5.5 | E5: ='Экономика дня'!C8*(1+0) -> 3.2 | F5: ='Экономика дня'!C9*(1+0) -> 2.8 | G5: =B5-SUM(C5:F5)-'Экономика дня'!C10-'Экономика дня'!C11-'Экономика дня'!C12-'Экономика дня'!C13 -> 14.1402 | H5: =G5*60*26-INDEX('Исходные данные'!$K$8:$K$29,MATCH("A21",'Исходные данные'!$J$8:$J$29,0))-3600 -> 6458.712 | I5: =IF(H5<0,"УБЫТОК — НУЖНО ИЗМЕНЕНИЕ",IF(G5/B5<25%,"НИЗКИЙ ЗАПАС","УСТОЙЧИВО")) -> УСТОЙЧИВО
A6: Цена -5% | B6: ='Экономика дня'!C5*(1+-0.05) -> 42.1325 | C6: ='Экономика дня'!C6*(1+0) -> 13.35 | D6: ='Экономика дня'!C7*(1+0) -> 5.5 | E6: ='Экономика дня'!C8*(1+0) -> 3.2 | F6: ='Экономика дня'!C9*(1+0) -> 2.8 | G6: =B6-SUM(C6:F6)-'Экономика дня'!C10-'Экономика дня'!C11-'Экономика дня'!C12-'Экономика дня'!C13 -> 11.9227 | H6: =G6*60*26-INDEX('Исходные данные'!$K$8:$K$29,MATCH("A21",'Исходные данные'!$J$8:$J$29,0))-3600 -> 2999.412 | I6: =IF(H6<0,"УБЫТОК — НУЖНО ИЗМЕНЕНИЕ",IF(G6/B6<25%,"НИЗКИЙ ЗАПАС","УСТОЙЧИВО")) -> УСТОЙЧИВО
A7: Цена -10% | B7: ='Экономика дня'!C5*(1+-0.1) -> 39.915 | C7: ='Экономика дня'!C6*(1+0) -> 13.35 | D7: ='Экономика дня'!C7*(1+0) -> 5.5 | E7: ='Экономика дня'!C8*(1+0) -> 3.2 | F7: ='Экономика дня'!C9*(1+0) -> 2.8 | G7: =B7-SUM(C7:F7)-'Экономика дня'!C10-'Экономика дня'!C11-'Экономика дня'!C12-'Экономика дня'!C13 -> 9.7052 | H7: =G7*60*26-INDEX('Исходные данные'!$K$8:$K$29,MATCH("A21",'Исходные данные'!$J$8:$J$29,0))-3600 -> -459.888 | I7: =IF(H7<0,"УБЫТОК — НУЖНО ИЗМЕНЕНИЕ",IF(G7/B7<25%,"НИЗКИЙ ЗАПАС","УСТОЙЧИВО")) -> УБЫТОК — НУЖНО ИЗМЕНЕНИЕ
A8: Сырьё +10% | B8: ='Экономика дня'!C5*(1+0) -> 44.35 | C8: ='Экономика дня'!C6*(1+0.1) -> 14.685 | D8: ='Экономика дня'!C7*(1+0) -> 5.5 | E8: ='Экономика дня'!C8*(1+0) -> 3.2 | F8: ='Экономика дня'!C9*(1+0) -> 2.8 | G8: =B8-SUM(C8:F8)-'Экономика дня'!C10-'Экономика дня'!C11-'Экономика дня'!C12-'Экономика дня'!C13 -> 12.8052 | H8: =G8*60*26-INDEX('Исходные данные'!$K$8:$K$29,MATCH("A21",'Исходные данные'!$J$8:$J$29,0))-3600 -> 4376.112 | I8: =IF(H8<0,"УБЫТОК — НУЖНО ИЗМЕНЕНИЕ",IF(G8/B8<25%,"НИЗКИЙ ЗАПАС","УСТОЙЧИВО")) -> УСТОЙЧИВО
A9: Сырьё +20% | B9: ='Экономика дня'!C5*(1+0) -> 44.35 | C9: ='Экономика дня'!C6*(1+0.2) -> 16.02 | D9: ='Экономика дня'!C7*(1+0) -> 5.5 | E9: ='Экономика дня'!C8*(1+0) -> 3.2 | F9: ='Экономика дня'!C9*(1+0) -> 2.8 | G9: =B9-SUM(C9:F9)-'Экономика дня'!C10-'Экономика дня'!C11-'Экономика дня'!C12-'Экономика дня'!C13 -> 11.4702 | H9: =G9*60*26-INDEX('Исходные данные'!$K$8:$K$29,MATCH("A21",'Исходные данные'!$J$8:$J$29,0))-3600 -> 2293.512 | I9: =IF(H9<0,"УБЫТОК — НУЖНО ИЗМЕНЕНИЕ",IF(G9/B9<25%,"НИЗКИЙ ЗАПАС","УСТОЙЧИВО")) -> УСТОЙЧИВО
A10: Кухня +20% | B10: ='Экономика дня'!C5*(1+0) -> 44.35 | C10: ='Экономика дня'!C6*(1+0) -> 13.35 | D10: ='Экономика дня'!C7*(1+0.2) -> 6.6 | E10: ='Экономика дня'!C8*(1+0) -> 3.2 | F10: ='Экономика дня'!C9*(1+0) -> 2.8 | G10: =B10-SUM(C10:F10)-'Экономика дня'!C10-'Экономика дня'!C11-'Экономика дня'!C12-'Экономика дня'!C13 -> 13.0402 | H10: =G10*60*26-INDEX('Исходные данные'!$K$8:$K$29,MATCH("A21",'Исходные данные'!$J$8:$J$29,0))-3600 -> 4742.712 | I10: =IF(H10<0,"УБЫТОК — НУЖНО ИЗМЕНЕНИЕ",IF(G10/B10<25%,"НИЗКИЙ ЗАПАС","УСТОЙЧИВО")) -> УСТОЙЧИВО
A11: Упаковка +20% | B11: ='Экономика дня'!C5*(1+0) -> 44.35 | C11: ='Экономика дня'!C6*(1+0) -> 13.35 | D11: ='Экономика дня'!C7*(1+0) -> 5.5 | E11: ='Экономика дня'!C8*(1+0.2) -> 3.84 | F11: ='Экономика дня'!C9*(1+0) -> 2.8 | G11: =B11-SUM(C11:F11)-'Экономика дня'!C10-'Экономика дня'!C11-'Экономика дня'!C12-'Экономика дня'!C13 -> 13.5002 | H11: =G11*60*26-INDEX('Исходные данные'!$K$8:$K$29,MATCH("A21",'Исходные данные'!$J$8:$J$29,0))-3600 -> 5460.312 | I11: =IF(H11<0,"УБЫТОК — НУЖНО ИЗМЕНЕНИЕ",IF(G11/B11<25%,"НИЗКИЙ ЗАПАС","УСТОЙЧИВО")) -> УСТОЙЧИВО
A12: Доставка +20% | B12: ='Экономика дня'!C5*(1+0) -> 44.35 | C12: ='Экономика дня'!C6*(1+0) -> 13.35 | D12: ='Экономика дня'!C7*(1+0) -> 5.5 | E12: ='Экономика дня'!C8*(1+0) -> 3.2 | F12: ='Экономика дня'!C9*(1+0.2) -> 3.36 | G12: =B12-SUM(C12:F12)-'Экономика дня'!C10-'Экономика дня'!C11-'Экономика дня'!C12-'Экономика дня'!C13 -> 13.5802 | H12: =G12*60*26-INDEX('Исходные данные'!$K$8:$K$29,MATCH("A21",'Исходные данные'!$J$8:$J$29,0))-3600 -> 5585.112 | I12: =IF(H12<0,"УБЫТОК — НУЖНО ИЗМЕНЕНИЕ",IF(G12/B12<25%,"НИЗКИЙ ЗАПАС","УСТОЙЧИВО")) -> УСТОЙЧИВО
A13: Комбинированный стресс | B13: ='Экономика дня'!C5*(1+-0.05) -> 42.1325 | C13: ='Экономика дня'!C6*(1+0.15) -> 15.3525 | D13: ='Экономика дня'!C7*(1+0.15) -> 6.325 | E13: ='Экономика дня'!C8*(1+0.1) -> 3.52 | F13: ='Экономика дня'!C9*(1+0.15) -> 3.22 | G13: =B13-SUM(C13:F13)-'Экономика дня'!C10-'Экономика дня'!C11-'Экономика дня'!C12-'Экономика дня'!C13 -> 8.3552 | H13: =G13*60*26-INDEX('Исходные данные'!$K$8:$K$29,MATCH("A21",'Исходные данные'!$J$8:$J$29,0))-3600 -> -2565.888 | I13: =IF(H13<0,"УБЫТОК — НУЖНО ИЗМЕНЕНИЕ",IF(G13/B13<25%,"НИЗКИЙ ЗАПАС","УСТОЙЧИВО")) -> УБЫТОК — НУЖНО ИЗМЕНЕНИЕ

Sheet Контроль
A1: Контроль финансовой модели
A2: Все строки должны показывать «ПРОЙДЕНО».
A4: Проверка | B4: Формула | C4: Результат | D4: Статус | E4: Комментарий
A5: Финансирование равно бюджету | B5: '=SUM('Движение денег'!B7:AK7) | C5: =SUM('Движение денег'!B7:AK7) -> 68000 | D5: 68000 | E5: =IF(ABS(C5-68000)<0.01,"ПРОЙДЕНО","ОШИБКА") -> ПРОЙДЕНО
A6: Нет деления на ноль | B6: '=COUNTIF('План 36 месяцев'!B19:AK19,"#DIV/0!") | C6: =COUNTIF('План 36 месяцев'!B19:AK19,"#DIV/0!") -> 0 | D6: 0 | E6: =IF(C6=0,"ПРОЙДЕНО","ОШИБКА") -> ПРОЙДЕНО
A7: Выручка = объём × цена | B7: '=SUMPRODUCT('План 36 месяцев'!B9:AK9,'План 36 месяцев'!B10:AK10)-SUM('План 36 месяцев'!B11:AK11) | C7: =SUMPRODUCT('План 36 месяцев'!B9:AK9,'План 36 месяцев'!B10:AK10)-SUM('План 36 месяцев'!B11:AK11) -> 0 | D7: 0 | E7: =IF(ABS(C7)<0.01,"ПРОЙДЕНО","ОШИБКА") -> ПРОЙДЕНО
A8: Касса сходится | B8: '='Движение денег'!AK16-SUM('Движение денег'!B15:AK15) | C8: ='Движение денег'!AK16-SUM('Движение денег'!B15:AK15) -> 0 | D8: 0 | E8: =IF(ABS(C8)<0.01,"ПРОЙДЕНО","ОШИБКА") -> ПРОЙДЕНО
A9: Маржа устойчивого объёма выше 25% | B9: '='Экономика дня'!C16 | C9: ='Экономика дня'!C16 -> 0.31883202 | D9: 0.25 | E9: =IF(C9>=D9,"ПРОЙДЕНО","ТРЕБУЕТ УЛУЧШЕНИЯ") -> ПРОЙДЕНО

Sheet Источники
A1: Источники расчётов
A2: Открытые ориентиры заменяются договорами и фактическими данными.
A4: Категория | B4: Источник | C4: Адрес | D4: Что использовано | E4: Ограничение
A5: Рынок | B5: Белстат | C5: https://www.belstat.gov.by/upload/iblock/0ec/tcgtty8e031wae223oyzhy9j9nudvv1e.pdf | D5: Население Молодечно и района | E5: Не доказывает платежеспособный спрос
A6: Конкуренты | B6: PROPORTSIYA | C6: https://proportsiya.by/ | D6: Цена рационов 1550–1800 ккал | E6: Не подтверждает спрос в Молодечно
A7: Сырьё | B7: GREEN | C7: https://green-dostavka.by/ | D7: Розничные цены продуктов | E7: Это верхний ориентир, не оптовое КП
A8: Пищевая ценность | B8: USDA FoodData Central | C8: https://fdc.nal.usda.gov/ | D8: Базовая пищевая ценность сырья | E8: Нужна проверка конкретных продуктов и выхода
A9: Упаковка | B9: Upakovki.by | C9: https://upakovki.by/ | D9: Минимальные тиражи и направление запроса | E9: Цена только по запросу
